nvscraper/__init__.py
nvscraper/nvutilities.py
nvscraper-0.1.3.dist-info/LICENSE
nvscraper-0.1.3.dist-info/METADATA
nvscraper-0.1.3.dist-info/WHEEL
nvscraper-0.1.3.dist-info/top_level.txt
nvscraper-0.1.3.dist-info/RECORD
