Metadata-Version: 2.1
Name: nvscraper
Version: 0.1.3
Summary: A simple Nvidia Graphics Cards Scraper to scrape data from Nvidia official API.
Author: covicale
Author-email: ag.covic@gmail.com
License: MIT License
License-File: LICENSE
Requires-Dist: requests
